README
setup.py
yatfs/__init__.py
yatfs/fs.py
yatfs/main.py
yatfs.egg-info/PKG-INFO
yatfs.egg-info/SOURCES.txt
yatfs.egg-info/dependency_links.txt
yatfs.egg-info/entry_points.txt
yatfs.egg-info/requires.txt
yatfs.egg-info/top_level.txt
yatfs/backend/__init__.py
yatfs/backend/deluge.py
yatfs/backend/noop.py
yatfs/tracker/__init__.py
yatfs/tracker/btn.py