Metadata-Version: 1.1
Name: yatfs
Version: 0.4.0
Summary: FUSE-based torrent-backed filesystem
Home-page: http://github.com/AllSeeingEyeTolledEweSew/yatfs
Author: AllSeeingEyeTolledEweSew
Author-email: allseeingeyetolledewesew@protonmail.com
License: Unlicense
Platform: UNKNOWN
Classifier: Development Status :: 4 - Beta
Classifier: Intended Audience :: End Users/Desktop
Classifier: License :: Public Domain
Classifier: Programming Language :: Python
Classifier: Topic :: Communications :: File Sharing
Classifier: Topic :: System :: Filesystems
Classifier: Topic :: System :: Networking
Classifier: Operating System :: POSIX :: Linux
Classifier: Operating System :: MacOS :: MacOS X
Classifier: Operating System :: POSIX :: BSD :: FreeBSD
Classifier: License :: Public Domain
